<ENTITY>
   <COLUMN>
      <FIELD>GUID</FIELD>
      <NAME></NAME>
      <TYPE>TEXT</TYPE>
      <LENGTH>36</LENGTH>
      <NOTNULL>N</NOTNULL>
      <STATUS>1</STATUS>
  </COLUMN>
   <COLUMN>
      <FIELD>BH</FIELD>
      <NAME>生产线编号</NAME>
      <TYPE>TEXT</TYPE>
      <LENGTH>30</LENGTH>
      <NOTNULL>N</NOTNULL>
      <STATUS>1</STATUS>
  </COLUMN>
   <COLUMN>
      <FIELD>NAME</FIELD>
      <NAME>生产线名</NAME>
      <TYPE>TEXT</TYPE>
      <LENGTH>30</LENGTH>
      <NOTNULL>N</NOTNULL>
      <STATUS>1</STATUS>
  </COLUMN>
   <COLUMN>
      <FIELD>CODE</FIELD>
      <NAME>生产线代码</NAME>
      <TYPE>TEXT</TYPE>
      <LENGTH>30</LENGTH>
      <NOTNULL>N</NOTNULL>
      <STATUS>1</STATUS>
  </COLUMN>
   <COLUMN>
      <FIELD>SSCJ</FIELD>
      <NAME>所属车间</NAME>
      <TYPE>TEXT</TYPE>
      <LENGTH>30</LENGTH>
      <NOTNULL>N</NOTNULL>
      <STATUS>1</STATUS>
  </COLUMN>
   <COLUMN>
      <FIELD>CJNSCX_CODE</FIELD>
      <NAME>车间内生产线代码</NAME>
      <TYPE>TEXT</TYPE>
      <LENGTH>36</LENGTH>
      <NOTNULL>N</NOTNULL>
      <STATUS>1</STATUS>
  </COLUMN>
   <COLUMN>
      <FIELD>GX</FIELD>
      <NAME>对应工序</NAME>
      <TYPE>TEXT</TYPE>
      <LENGTH>30</LENGTH>
      <NOTNULL>N</NOTNULL>
      <STATUS>1</STATUS>
  </COLUMN>
   <COLUMN>
      <FIELD>SCX_NAME1</FIELD>
      <NAME>该生产线班次1对应计件生产线名</NAME>
      <TYPE>TEXT</TYPE>
      <LENGTH>20</LENGTH>
      <NOTNULL>N</NOTNULL>
      <STATUS>1</STATUS>
  </COLUMN>
   <COLUMN>
      <FIELD>JYSCX</FIELD>
      <NAME>对应检验生产线</NAME>
      <TYPE>TEXT</TYPE>
      <LENGTH>30</LENGTH>
      <NOTNULL>N</NOTNULL>
      <STATUS>1</STATUS>
  </COLUMN>
   <COLUMN>
      <FIELD>SCX_NAME2</FIELD>
      <NAME>该生产线班次2对应计件生产线名</NAME>
      <TYPE>TEXT</TYPE>
      <LENGTH>20</LENGTH>
      <NOTNULL>N</NOTNULL>
      <STATUS>1</STATUS>
  </COLUMN>
   <COLUMN>
      <FIELD>BC_NAME3</FIELD>
      <NAME>班次3名</NAME>
      <TYPE>TEXT</TYPE>
      <LENGTH>30</LENGTH>
      <NOTNULL>N</NOTNULL>
      <STATUS>1</STATUS>
  </COLUMN>
   <COLUMN>
      <FIELD>SCX_NAME3</FIELD>
      <NAME>该生产线班次3对应计件生产线名</NAME>
      <TYPE>TEXT</TYPE>
      <LENGTH>20</LENGTH>
      <NOTNULL>N</NOTNULL>
      <STATUS>1</STATUS>
  </COLUMN>
   <COLUMN>
      <FIELD>GZ1_CODE</FIELD>
      <NAME>该生产线工种1</NAME>
      <TYPE>TEXT</TYPE>
      <LENGTH>20</LENGTH>
      <NOTNULL>N</NOTNULL>
      <STATUS>1</STATUS>
  </COLUMN>
   <COLUMN>
      <FIELD>GZ2_CODE</FIELD>
      <NAME>该生产线工种2</NAME>
      <TYPE>TEXT</TYPE>
      <LENGTH>20</LENGTH>
      <NOTNULL>N</NOTNULL>
      <STATUS>1</STATUS>
  </COLUMN>
   <COLUMN>
      <FIELD>GZ3_CODE</FIELD>
      <NAME>该生产线工种3</NAME>
      <TYPE>TEXT</TYPE>
      <LENGTH>20</LENGTH>
      <NOTNULL>N</NOTNULL>
      <STATUS>1</STATUS>
  </COLUMN>
   <COLUMN>
      <FIELD>GZ4_CODE</FIELD>
      <NAME>该生产线工种4</NAME>
      <TYPE>TEXT</TYPE>
      <LENGTH>20</LENGTH>
      <NOTNULL>N</NOTNULL>
      <STATUS>1</STATUS>
  </COLUMN>
   <COLUMN>
      <FIELD>GZ5_CODE</FIELD>
      <NAME>该生产线工种5</NAME>
      <TYPE>TEXT</TYPE>
      <LENGTH>20</LENGTH>
      <NOTNULL>N</NOTNULL>
      <STATUS>1</STATUS>
  </COLUMN>
   <COLUMN>
      <FIELD>SXHD</FIELD>
      <NAME>默认砂箱厚度/cm(可变)</NAME>
      <TYPE>NUM</TYPE>
      <LENGTH>9</LENGTH>
      <NOTNULL>N</NOTNULL>
      <STATUS>1</STATUS>
  </COLUMN>
   <COLUMN>
      <FIELD>SXGD</FIELD>
      <NAME>砂箱高度/cm(固定)</NAME>
      <TYPE>NUM</TYPE>
      <LENGTH>9</LENGTH>
      <NOTNULL>N</NOTNULL>
      <STATUS>1</STATUS>
  </COLUMN>
   <COLUMN>
      <FIELD>SXKD</FIELD>
      <NAME>砂箱宽度/cm(固定)</NAME>
      <TYPE>NUM</TYPE>
      <LENGTH>9</LENGTH>
      <NOTNULL>N</NOTNULL>
      <STATUS>1</STATUS>
  </COLUMN>
   <COLUMN>
      <FIELD>SXMD</FIELD>
      <NAME>砂箱密度kg/cm^3</NAME>
      <TYPE>NUM</TYPE>
      <LENGTH>9</LENGTH>
      <NOTNULL>N</NOTNULL>
      <STATUS>1</STATUS>
  </COLUMN>
   <COLUMN>
      <FIELD>LLSSH</FIELD>
      <NAME>理论砂损耗百分比</NAME>
      <TYPE>NUM</TYPE>
      <LENGTH>9</LENGTH>
      <NOTNULL>N</NOTNULL>
      <STATUS>1</STATUS>
  </COLUMN>
   <COLUMN>
      <FIELD>LLTSSH</FIELD>
      <NAME>理论铁水损耗百分比</NAME>
      <TYPE>NUM</TYPE>
      <LENGTH>9</LENGTH>
      <NOTNULL>N</NOTNULL>
      <STATUS>1</STATUS>
  </COLUMN>
   <COLUMN>
      <FIELD>KYMJLX</FIELD>
      <NAME>可用模具类型</NAME>
      <TYPE>TEXT</TYPE>
      <LENGTH>20</LENGTH>
      <NOTNULL>N</NOTNULL>
      <STATUS>1</STATUS>
  </COLUMN>
   <COLUMN>
      <FIELD>KYMJLX1</FIELD>
      <NAME>优先使用模具类型1</NAME>
      <TYPE>TEXT</TYPE>
      <LENGTH>20</LENGTH>
      <NOTNULL>N</NOTNULL>
      <STATUS>1</STATUS>
  </COLUMN>
   <COLUMN>
      <FIELD>KYMJLX2</FIELD>
      <NAME>优先使用模具类型2</NAME>
      <TYPE>TEXT</TYPE>
      <LENGTH>20</LENGTH>
      <NOTNULL>N</NOTNULL>
      <STATUS>1</STATUS>
  </COLUMN>
   <COLUMN>
      <FIELD>KYMJLX3</FIELD>
      <NAME>优先使用模具类型3</NAME>
      <TYPE>TEXT</TYPE>
      <LENGTH>20</LENGTH>
      <NOTNULL>N</NOTNULL>
      <STATUS>1</STATUS>
  </COLUMN>
   <COLUMN>
      <FIELD>PL1</FIELD>
      <NAME>配料1名</NAME>
      <TYPE>TEXT</TYPE>
      <LENGTH>20</LENGTH>
      <NOTNULL>N</NOTNULL>
      <STATUS>1</STATUS>
  </COLUMN>
   <COLUMN>
      <FIELD>PL2</FIELD>
      <NAME>配料2名</NAME>
      <TYPE>TEXT</TYPE>
      <LENGTH>20</LENGTH>
      <NOTNULL>N</NOTNULL>
      <STATUS>1</STATUS>
  </COLUMN>
   <COLUMN>
      <FIELD>PL3</FIELD>
      <NAME>配料3名</NAME>
      <TYPE>TEXT</TYPE>
      <LENGTH>20</LENGTH>
      <NOTNULL>N</NOTNULL>
      <STATUS>1</STATUS>
  </COLUMN>
   <COLUMN>
      <FIELD>PL4</FIELD>
      <NAME>配料4名</NAME>
      <TYPE>TEXT</TYPE>
      <LENGTH>20</LENGTH>
      <NOTNULL>N</NOTNULL>
      <STATUS>1</STATUS>
  </COLUMN>
   <COLUMN>
      <FIELD>PL5</FIELD>
      <NAME>配料5名</NAME>
      <TYPE>TEXT</TYPE>
      <LENGTH>20</LENGTH>
      <NOTNULL>N</NOTNULL>
      <STATUS>1</STATUS>
  </COLUMN>
   <COLUMN>
      <FIELD>PL6</FIELD>
      <NAME>配料6名</NAME>
      <TYPE>TEXT</TYPE>
      <LENGTH>20</LENGTH>
      <NOTNULL>N</NOTNULL>
      <STATUS>1</STATUS>
  </COLUMN>
   <COLUMN>
      <FIELD>PL7</FIELD>
      <NAME>配料7名</NAME>
      <TYPE>TEXT</TYPE>
      <LENGTH>20</LENGTH>
      <NOTNULL>N</NOTNULL>
      <STATUS>1</STATUS>
  </COLUMN>
   <COLUMN>
      <FIELD>PL8</FIELD>
      <NAME>配料8名</NAME>
      <TYPE>TEXT</TYPE>
      <LENGTH>20</LENGTH>
      <NOTNULL>N</NOTNULL>
      <STATUS>1</STATUS>
  </COLUMN>
   <COLUMN>
      <FIELD>PL1_PARAM</FIELD>
      <NAME>计算配料1用量使用参数</NAME>
      <TYPE>TEXT</TYPE>
      <LENGTH>30</LENGTH>
      <NOTNULL>N</NOTNULL>
      <STATUS>1</STATUS>
  </COLUMN>
   <COLUMN>
      <FIELD>PL2_PARAM</FIELD>
      <NAME>计算配料2用量使用参数</NAME>
      <TYPE>TEXT</TYPE>
      <LENGTH>30</LENGTH>
      <NOTNULL>N</NOTNULL>
      <STATUS>1</STATUS>
  </COLUMN>
   <COLUMN>
      <FIELD>PL3_PARAM</FIELD>
      <NAME>计算配料3用量使用参数</NAME>
      <TYPE>TEXT</TYPE>
      <LENGTH>30</LENGTH>
      <NOTNULL>N</NOTNULL>
      <STATUS>1</STATUS>
  </COLUMN>
   <COLUMN>
      <FIELD>PL4_PARAM</FIELD>
      <NAME>计算配料4用量使用参数</NAME>
      <TYPE>TEXT</TYPE>
      <LENGTH>30</LENGTH>
      <NOTNULL>N</NOTNULL>
      <STATUS>1</STATUS>
  </COLUMN>
   <COLUMN>
      <FIELD>PL5_PARAM</FIELD>
      <NAME>计算配料5用量使用参数</NAME>
      <TYPE>TEXT</TYPE>
      <LENGTH>30</LENGTH>
      <NOTNULL>N</NOTNULL>
      <STATUS>1</STATUS>
  </COLUMN>
   <COLUMN>
      <FIELD>PL6_PARAM</FIELD>
      <NAME>计算配料6用量使用参数</NAME>
      <TYPE>TEXT</TYPE>
      <LENGTH>30</LENGTH>
      <NOTNULL>N</NOTNULL>
      <STATUS>1</STATUS>
  </COLUMN>
   <COLUMN>
      <FIELD>PL7_PARAM</FIELD>
      <NAME>计算配料7用量使用参数</NAME>
      <TYPE>TEXT</TYPE>
      <LENGTH>30</LENGTH>
      <NOTNULL>N</NOTNULL>
      <STATUS>1</STATUS>
  </COLUMN>
   <COLUMN>
      <FIELD>PL8_PARAM</FIELD>
      <NAME>计算配料8用量使用参数</NAME>
      <TYPE>TEXT</TYPE>
      <LENGTH>30</LENGTH>
      <NOTNULL>N</NOTNULL>
      <STATUS>1</STATUS>
  </COLUMN>
   <COLUMN>
      <FIELD>PL1_DYCSBZ</FIELD>
      <NAME>配料1对应参数比值</NAME>
      <TYPE>NUM</TYPE>
      <LENGTH>9</LENGTH>
      <NOTNULL>N</NOTNULL>
      <STATUS>1</STATUS>
  </COLUMN>
   <COLUMN>
      <FIELD>PL2_DYCSBZ</FIELD>
      <NAME>配料2对应参数比值</NAME>
      <TYPE>NUM</TYPE>
      <LENGTH>9</LENGTH>
      <NOTNULL>N</NOTNULL>
      <STATUS>1</STATUS>
  </COLUMN>
   <COLUMN>
      <FIELD>PL3_DYCSBZ</FIELD>
      <NAME>配料3对应参数比值</NAME>
      <TYPE>NUM</TYPE>
      <LENGTH>9</LENGTH>
      <NOTNULL>N</NOTNULL>
      <STATUS>1</STATUS>
  </COLUMN>
   <COLUMN>
      <FIELD>PL4_DYCSBZ</FIELD>
      <NAME>配料4对应参数比值</NAME>
      <TYPE>NUM</TYPE>
      <LENGTH>9</LENGTH>
      <NOTNULL>N</NOTNULL>
      <STATUS>1</STATUS>
  </COLUMN>
   <COLUMN>
      <FIELD>PL5_DYCSBZ</FIELD>
      <NAME>配料5对应参数比值</NAME>
      <TYPE>NUM</TYPE>
      <LENGTH>9</LENGTH>
      <NOTNULL>N</NOTNULL>
      <STATUS>1</STATUS>
  </COLUMN>
   <COLUMN>
      <FIELD>PL6_DYCSBZ</FIELD>
      <NAME>配料6对应参数比值</NAME>
      <TYPE>NUM</TYPE>
      <LENGTH>9</LENGTH>
      <NOTNULL>N</NOTNULL>
      <STATUS>1</STATUS>
  </COLUMN>
   <COLUMN>
      <FIELD>PL7_DYCSBZ</FIELD>
      <NAME>配料7对应参数比值</NAME>
      <TYPE>NUM</TYPE>
      <LENGTH>9</LENGTH>
      <NOTNULL>N</NOTNULL>
      <STATUS>1</STATUS>
  </COLUMN>
   <COLUMN>
      <FIELD>PL8_DYCSBZ</FIELD>
      <NAME>配料8对应参数比值</NAME>
      <TYPE>NUM</TYPE>
      <LENGTH>9</LENGTH>
      <NOTNULL>N</NOTNULL>
      <STATUS>1</STATUS>
  </COLUMN>
   <COLUMN>
      <FIELD>PL1_CKCK</FIELD>
      <NAME>配料1默认出库仓库</NAME>
      <TYPE>TEXT</TYPE>
      <LENGTH>20</LENGTH>
      <NOTNULL>N</NOTNULL>
      <STATUS>1</STATUS>
  </COLUMN>
   <COLUMN>
      <FIELD>PL2_CKCK</FIELD>
      <NAME>配料2默认出库仓库</NAME>
      <TYPE>TEXT</TYPE>
      <LENGTH>20</LENGTH>
      <NOTNULL>N</NOTNULL>
      <STATUS>1</STATUS>
  </COLUMN>
   <COLUMN>
      <FIELD>PL3_CKCK</FIELD>
      <NAME>配料3默认出库仓库</NAME>
      <TYPE>TEXT</TYPE>
      <LENGTH>20</LENGTH>
      <NOTNULL>N</NOTNULL>
      <STATUS>1</STATUS>
  </COLUMN>
   <COLUMN>
      <FIELD>PL4_CKCK</FIELD>
      <NAME>配料4默认出库仓库</NAME>
      <TYPE>TEXT</TYPE>
      <LENGTH>20</LENGTH>
      <NOTNULL>N</NOTNULL>
      <STATUS>1</STATUS>
  </COLUMN>
   <COLUMN>
      <FIELD>PL5_CKCK</FIELD>
      <NAME>配料5默认出库仓库</NAME>
      <TYPE>TEXT</TYPE>
      <LENGTH>20</LENGTH>
      <NOTNULL>N</NOTNULL>
      <STATUS>1</STATUS>
  </COLUMN>
   <COLUMN>
      <FIELD>PL6_CKCK</FIELD>
      <NAME>配料6默认出库仓库</NAME>
      <TYPE>TEXT</TYPE>
      <LENGTH>20</LENGTH>
      <NOTNULL>N</NOTNULL>
      <STATUS>1</STATUS>
  </COLUMN>
   <COLUMN>
      <FIELD>PL7_CKCK</FIELD>
      <NAME>配料7默认出库仓库</NAME>
      <TYPE>TEXT</TYPE>
      <LENGTH>20</LENGTH>
      <NOTNULL>N</NOTNULL>
      <STATUS>1</STATUS>
  </COLUMN>
   <COLUMN>
      <FIELD>PL8_CKCK</FIELD>
      <NAME>配料8默认出库仓库</NAME>
      <TYPE>TEXT</TYPE>
      <LENGTH>20</LENGTH>
      <NOTNULL>N</NOTNULL>
      <STATUS>1</STATUS>
  </COLUMN>
   <COLUMN>
      <FIELD>CP1</FIELD>
      <NAME>产品1名</NAME>
      <TYPE>TEXT</TYPE>
      <LENGTH>20</LENGTH>
      <NOTNULL>N</NOTNULL>
      <STATUS>1</STATUS>
  </COLUMN>
   <COLUMN>
      <FIELD>CP2</FIELD>
      <NAME>产品2名</NAME>
      <TYPE>TEXT</TYPE>
      <LENGTH>20</LENGTH>
      <NOTNULL>N</NOTNULL>
      <STATUS>1</STATUS>
  </COLUMN>
   <COLUMN>
      <FIELD>CP3</FIELD>
      <NAME>产品3名</NAME>
      <TYPE>TEXT</TYPE>
      <LENGTH>20</LENGTH>
      <NOTNULL>N</NOTNULL>
      <STATUS>1</STATUS>
  </COLUMN>
   <COLUMN>
      <FIELD>CP4</FIELD>
      <NAME>产品4名</NAME>
      <TYPE>TEXT</TYPE>
      <LENGTH>20</LENGTH>
      <NOTNULL>N</NOTNULL>
      <STATUS>1</STATUS>
  </COLUMN>
   <COLUMN>
      <FIELD>CP5</FIELD>
      <NAME>产品5名</NAME>
      <TYPE>TEXT</TYPE>
      <LENGTH>20</LENGTH>
      <NOTNULL>N</NOTNULL>
      <STATUS>1</STATUS>
  </COLUMN>
   <COLUMN>
      <FIELD>CP6</FIELD>
      <NAME>产品6名</NAME>
      <TYPE>TEXT</TYPE>
      <LENGTH>20</LENGTH>
      <NOTNULL>N</NOTNULL>
      <STATUS>1</STATUS>
  </COLUMN>
   <COLUMN>
      <FIELD>CP7</FIELD>
      <NAME>产品7名</NAME>
      <TYPE>TEXT</TYPE>
      <LENGTH>20</LENGTH>
      <NOTNULL>N</NOTNULL>
      <STATUS>1</STATUS>
  </COLUMN>
   <COLUMN>
      <FIELD>CP8</FIELD>
      <NAME>产品8名</NAME>
      <TYPE>TEXT</TYPE>
      <LENGTH>20</LENGTH>
      <NOTNULL>N</NOTNULL>
      <STATUS>1</STATUS>
  </COLUMN>
   <COLUMN>
      <FIELD>CP1_PARAM</FIELD>
      <NAME>产品1使用参数</NAME>
      <TYPE>TEXT</TYPE>
      <LENGTH>30</LENGTH>
      <NOTNULL>N</NOTNULL>
      <STATUS>1</STATUS>
  </COLUMN>
   <COLUMN>
      <FIELD>CP2_PARAM</FIELD>
      <NAME>产品2使用参数</NAME>
      <TYPE>TEXT</TYPE>
      <LENGTH>30</LENGTH>
      <NOTNULL>N</NOTNULL>
      <STATUS>1</STATUS>
  </COLUMN>
   <COLUMN>
      <FIELD>CP3_PARAM</FIELD>
      <NAME>产品3使用参数</NAME>
      <TYPE>TEXT</TYPE>
      <LENGTH>30</LENGTH>
      <NOTNULL>N</NOTNULL>
      <STATUS>1</STATUS>
  </COLUMN>
   <COLUMN>
      <FIELD>CP4_PARAM</FIELD>
      <NAME>产品4使用参数</NAME>
      <TYPE>TEXT</TYPE>
      <LENGTH>30</LENGTH>
      <NOTNULL>N</NOTNULL>
      <STATUS>1</STATUS>
  </COLUMN>
   <COLUMN>
      <FIELD>CP5_PARAM</FIELD>
      <NAME>产品5使用参数</NAME>
      <TYPE>TEXT</TYPE>
      <LENGTH>30</LENGTH>
      <NOTNULL>N</NOTNULL>
      <STATUS>1</STATUS>
  </COLUMN>
   <COLUMN>
      <FIELD>CP6_PARAM</FIELD>
      <NAME>产品6使用参数</NAME>
      <TYPE>TEXT</TYPE>
      <LENGTH>30</LENGTH>
      <NOTNULL>N</NOTNULL>
      <STATUS>1</STATUS>
  </COLUMN>
   <COLUMN>
      <FIELD>CP7_PARAM</FIELD>
      <NAME>产品7使用参数</NAME>
      <TYPE>TEXT</TYPE>
      <LENGTH>30</LENGTH>
      <NOTNULL>N</NOTNULL>
      <STATUS>1</STATUS>
  </COLUMN>
   <COLUMN>
      <FIELD>CP8_PARAM</FIELD>
      <NAME>产品8使用参数</NAME>
      <TYPE>TEXT</TYPE>
      <LENGTH>30</LENGTH>
      <NOTNULL>N</NOTNULL>
      <STATUS>1</STATUS>
  </COLUMN>
   <COLUMN>
      <FIELD>CP1_DYCSBZ</FIELD>
      <NAME>产品1对应参数比值</NAME>
      <TYPE>NUM</TYPE>
      <LENGTH>9</LENGTH>
      <NOTNULL>N</NOTNULL>
      <STATUS>1</STATUS>
  </COLUMN>
   <COLUMN>
      <FIELD>CP2_DYCSBZ</FIELD>
      <NAME>产品2对应参数比值</NAME>
      <TYPE>NUM</TYPE>
      <LENGTH>9</LENGTH>
      <NOTNULL>N</NOTNULL>
      <STATUS>1</STATUS>
  </COLUMN>
   <COLUMN>
      <FIELD>CP3_DYCSBZ</FIELD>
      <NAME>产品3对应参数比值</NAME>
      <TYPE>NUM</TYPE>
      <LENGTH>9</LENGTH>
      <NOTNULL>N</NOTNULL>
      <STATUS>1</STATUS>
  </COLUMN>
   <COLUMN>
      <FIELD>CP4_DYCSBZ</FIELD>
      <NAME>产品4对应参数比值</NAME>
      <TYPE>NUM</TYPE>
      <LENGTH>9</LENGTH>
      <NOTNULL>N</NOTNULL>
      <STATUS>1</STATUS>
  </COLUMN>
   <COLUMN>
      <FIELD>CP5_DYCSBZ</FIELD>
      <NAME>产品5对应参数比值</NAME>
      <TYPE>NUM</TYPE>
      <LENGTH>9</LENGTH>
      <NOTNULL>N</NOTNULL>
      <STATUS>1</STATUS>
  </COLUMN>
   <COLUMN>
      <FIELD>CP6_DYCSBZ</FIELD>
      <NAME>产品6对应参数比值</NAME>
      <TYPE>NUM</TYPE>
      <LENGTH>9</LENGTH>
      <NOTNULL>N</NOTNULL>
      <STATUS>1</STATUS>
  </COLUMN>
   <COLUMN>
      <FIELD>CP7_DYCSBZ</FIELD>
      <NAME>产品7对应参数比值</NAME>
      <TYPE>NUM</TYPE>
      <LENGTH>9</LENGTH>
      <NOTNULL>N</NOTNULL>
      <STATUS>1</STATUS>
  </COLUMN>
   <COLUMN>
      <FIELD>CP8_DYCSBZ</FIELD>
      <NAME>产品8对应参数比值</NAME>
      <TYPE>NUM</TYPE>
      <LENGTH>9</LENGTH>
      <NOTNULL>N</NOTNULL>
      <STATUS>1</STATUS>
  </COLUMN>
   <COLUMN>
      <FIELD>CP1_JSGS</FIELD>
      <NAME>产品1依配料计算公式</NAME>
      <TYPE>TEXT</TYPE>
      <LENGTH>200</LENGTH>
      <NOTNULL>N</NOTNULL>
      <STATUS>1</STATUS>
  </COLUMN>
   <COLUMN>
      <FIELD>CP2_JSGS</FIELD>
      <NAME>产品2依配料计算公式</NAME>
      <TYPE>TEXT</TYPE>
      <LENGTH>200</LENGTH>
      <NOTNULL>N</NOTNULL>
      <STATUS>1</STATUS>
  </COLUMN>
   <COLUMN>
      <FIELD>CP3_JSGS</FIELD>
      <NAME>产品3依配料计算公式</NAME>
      <TYPE>TEXT</TYPE>
      <LENGTH>200</LENGTH>
      <NOTNULL>N</NOTNULL>
      <STATUS>1</STATUS>
  </COLUMN>
   <COLUMN>
      <FIELD>CP4_JSGS</FIELD>
      <NAME>产品4依配料计算公式</NAME>
      <TYPE>TEXT</TYPE>
      <LENGTH>200</LENGTH>
      <NOTNULL>N</NOTNULL>
      <STATUS>1</STATUS>
  </COLUMN>
   <COLUMN>
      <FIELD>CP5_JSGS</FIELD>
      <NAME>产品5依配料计算公式</NAME>
      <TYPE>TEXT</TYPE>
      <LENGTH>200</LENGTH>
      <NOTNULL>N</NOTNULL>
      <STATUS>1</STATUS>
  </COLUMN>
   <COLUMN>
      <FIELD>CP6_JSGS</FIELD>
      <NAME>产品6依配料计算公式</NAME>
      <TYPE>TEXT</TYPE>
      <LENGTH>200</LENGTH>
      <NOTNULL>N</NOTNULL>
      <STATUS>1</STATUS>
  </COLUMN>
   <COLUMN>
      <FIELD>CP7_JSGS</FIELD>
      <NAME>产品7依配料计算公式</NAME>
      <TYPE>TEXT</TYPE>
      <LENGTH>200</LENGTH>
      <NOTNULL>N</NOTNULL>
      <STATUS>1</STATUS>
  </COLUMN>
   <COLUMN>
      <FIELD>CP8_JSGS</FIELD>
      <NAME>产品8依配料计算公式</NAME>
      <TYPE>TEXT</TYPE>
      <LENGTH>200</LENGTH>
      <NOTNULL>N</NOTNULL>
      <STATUS>1</STATUS>
  </COLUMN>
   <COLUMN>
      <FIELD>CP1_RKCK</FIELD>
      <NAME>产品1默认入库仓库</NAME>
      <TYPE>TEXT</TYPE>
      <LENGTH>30</LENGTH>
      <NOTNULL>N</NOTNULL>
      <STATUS>1</STATUS>
  </COLUMN>
   <COLUMN>
      <FIELD>CP2_RKCK</FIELD>
      <NAME>产品2默认入库仓库</NAME>
      <TYPE>TEXT</TYPE>
      <LENGTH>30</LENGTH>
      <NOTNULL>N</NOTNULL>
      <STATUS>1</STATUS>
  </COLUMN>
   <COLUMN>
      <FIELD>CP3_RKCK</FIELD>
      <NAME>产品3默认入库仓库</NAME>
      <TYPE>TEXT</TYPE>
      <LENGTH>30</LENGTH>
      <NOTNULL>N</NOTNULL>
      <STATUS>1</STATUS>
  </COLUMN>
   <COLUMN>
      <FIELD>CP4_RKCK</FIELD>
      <NAME>产品4默认入库仓库</NAME>
      <TYPE>TEXT</TYPE>
      <LENGTH>30</LENGTH>
      <NOTNULL>N</NOTNULL>
      <STATUS>1</STATUS>
  </COLUMN>
   <COLUMN>
      <FIELD>CP5_RKCK</FIELD>
      <NAME>产品5默认入库仓库</NAME>
      <TYPE>TEXT</TYPE>
      <LENGTH>30</LENGTH>
      <NOTNULL>N</NOTNULL>
      <STATUS>1</STATUS>
  </COLUMN>
   <COLUMN>
      <FIELD>CP6_RKCK</FIELD>
      <NAME>产品6默认入库仓库</NAME>
      <TYPE>TEXT</TYPE>
      <LENGTH>30</LENGTH>
      <NOTNULL>N</NOTNULL>
      <STATUS>1</STATUS>
  </COLUMN>
   <COLUMN>
      <FIELD>CP7_RKCK</FIELD>
      <NAME>产品7默认入库仓库</NAME>
      <TYPE>TEXT</TYPE>
      <LENGTH>30</LENGTH>
      <NOTNULL>N</NOTNULL>
      <STATUS>1</STATUS>
  </COLUMN>
   <COLUMN>
      <FIELD>CP8_RKCK</FIELD>
      <NAME>产品8默认入库仓库</NAME>
      <TYPE>TEXT</TYPE>
      <LENGTH>30</LENGTH>
      <NOTNULL>N</NOTNULL>
      <STATUS>1</STATUS>
  </COLUMN>
   <COLUMN>
      <FIELD>REMARK</FIELD>
      <NAME>备注</NAME>
      <TYPE>TEXT</TYPE>
      <LENGTH>300</LENGTH>
      <NOTNULL>N</NOTNULL>
      <STATUS>1</STATUS>
  </COLUMN>
   <COLUMN>
      <FIELD>CREATE_USER</FIELD>
      <NAME></NAME>
      <TYPE>TEXT</TYPE>
      <LENGTH>20</LENGTH>
      <NOTNULL>N</NOTNULL>
      <STATUS>1</STATUS>
  </COLUMN>
   <COLUMN>
      <FIELD>CREATE_USER_NAME</FIELD>
      <NAME></NAME>
      <TYPE>TEXT</TYPE>
      <LENGTH>50</LENGTH>
      <NOTNULL>N</NOTNULL>
      <STATUS>1</STATUS>
  </COLUMN>
   <COLUMN>
      <FIELD>CREATE_DATE</FIELD>
      <NAME></NAME>
      <TYPE>DATE</TYPE>
      <LENGTH>8</LENGTH>
      <NOTNULL>N</NOTNULL>
      <STATUS>1</STATUS>
  </COLUMN>
   <COLUMN>
      <FIELD>UPDATE_USER</FIELD>
      <NAME></NAME>
      <TYPE>TEXT</TYPE>
      <LENGTH>20</LENGTH>
      <NOTNULL>N</NOTNULL>
      <STATUS>1</STATUS>
  </COLUMN>
   <COLUMN>
      <FIELD>UPDATE_USER_NAME</FIELD>
      <NAME></NAME>
      <TYPE>TEXT</TYPE>
      <LENGTH>50</LENGTH>
      <NOTNULL>N</NOTNULL>
      <STATUS>1</STATUS>
  </COLUMN>
   <COLUMN>
      <FIELD>UPDATE_DATE</FIELD>
      <NAME></NAME>
      <TYPE>DATE</TYPE>
      <LENGTH>8</LENGTH>
      <NOTNULL>N</NOTNULL>
      <STATUS>1</STATUS>
  </COLUMN>
   <COLUMN>
      <FIELD>COMPANY_CODE</FIELD>
      <NAME></NAME>
      <TYPE>TEXT</TYPE>
      <LENGTH>50</LENGTH>
      <NOTNULL>N</NOTNULL>
      <STATUS>1</STATUS>
  </COLUMN>
   <COLUMN>
      <FIELD>COMPANY_NAME</FIELD>
      <NAME></NAME>
      <TYPE>TEXT</TYPE>
      <LENGTH>200</LENGTH>
      <NOTNULL>N</NOTNULL>
      <STATUS>1</STATUS>
  </COLUMN>

</ENTITY>